helper.py
silent_installation.py
simufact.py
silent_installation-1.2.0.dist-info/METADATA
silent_installation-1.2.0.dist-info/WHEEL
silent_installation-1.2.0.dist-info/entry_points.txt
silent_installation-1.2.0.dist-info/top_level.txt
silent_installation-1.2.0.dist-info/RECORD
