Metadata-Version: 2.4
Name: silent-installation
Version: 1.2.0
Summary: install simufact products silently.
Author-email: qun <qun.chen@hexagon.com>
License: MIT License
Keywords: silent,install
Requires-Python: >=3.0
